sample_package/__init__.py
sample_package/__version__.py
sample_package/another_process.py
sample_package/main.py
learn_python_ms-0.1.6.dist-info/LICENSE
learn_python_ms-0.1.6.dist-info/METADATA
learn_python_ms-0.1.6.dist-info/WHEEL
learn_python_ms-0.1.6.dist-info/top_level.txt
learn_python_ms-0.1.6.dist-info/RECORD
