Metadata-Version: 2.1
Name: learn-python-ms
Version: 0.1.6
Summary: This is description of learn python project.
Home-page: https://github.com/mandheer/learn_python
Author: Mandheer Pabreja
Author-email: mandheer@pabreja.in
License: UNKNOWN
Platform: UNKNOWN
Classifier: License :: OSI Approved :: MIT License
Classifier: Programming Language :: Python
Classifier: Programming Language :: Python :: 3
Classifier: Programming Language :: Python :: 3.8
Classifier: Programming Language :: Python :: Implementation :: CPython
Classifier: Programming Language :: Python :: Implementation :: PyPy
Requires-Python: >=3.8.0
